hpcomt/__init__.py
hpcomt-0.1.dist-info/LICENSE
hpcomt-0.1.dist-info/METADATA
hpcomt-0.1.dist-info/WHEEL
hpcomt-0.1.dist-info/top_level.txt
hpcomt-0.1.dist-info/RECORD
